setup.cfg
setup.py
autoextractor/__init__.py
autoextractor/autoextractor.py
autoextractor/settings.py
autoextractor.egg-info/PKG-INFO
autoextractor.egg-info/SOURCES.txt
autoextractor.egg-info/dependency_links.txt
autoextractor.egg-info/entry_points.txt
autoextractor.egg-info/requires.txt
autoextractor.egg-info/top_level.txt