Metadata-Version: 1.0
Name: autoextractor
Version: 1.02
Summary: Auto copy and extraction tool
Home-page: UNKNOWN
Author: UNKNOWN
Author-email: UNKNOWN
License: UNKNOWN
Platform: UNKNOWN
